subprocesshidden/README.MD
subprocesshidden/__init__.py
subprocesshidden/requirements.txt
subprocesshidden/thirdparty.json
subprocesshidden-0.11.dist-info/LICENSE.rst
subprocesshidden-0.11.dist-info/METADATA
subprocesshidden-0.11.dist-info/WHEEL
subprocesshidden-0.11.dist-info/top_level.txt
subprocesshidden-0.11.dist-info/RECORD
