Metadata-Version: 2.1
Name: subprocesshidden
Version: 0.11
Summary: Executes subprocesses without console (Windows), reads stdout/stderr
Home-page: https://github.com/hansalemaos/subprocesshidden
Author: Johannes Fischer
Author-email: aulasparticularesdealemaosp@gmail.com
License: MIT
Keywords: subprocess,hidden
Classifier: Development Status :: 4 - Beta
Classifier: Programming Language :: Python :: 3 :: Only
Classifier: Programming Language :: Python :: 3.10
Classifier: Topic :: Software Development :: Libraries :: Python Modules
Classifier: Topic :: Utilities
License-File: LICENSE.rst
Requires-Dist: shortpath83
